{"summaries":[{"symbol":{"__symbol":0},"metadata":{"__symbolic":"function","parameters":["http"],"value":{"__symbolic":"new","expression":{"__symbol":1},"arguments":[{"__symbolic":"reference","name":"http"},"./i18n/",".json"]}}},{"symbol":{"__symbol":2},"metadata":{"__symbolic":"class"},"type":{"summaryKind":2,"type":{"reference":{"__symbol":2},"diDeps":[],"lifecycleHooks":[]},"entryComponents":[{"reference":{"__symbol":3}},{"reference":{"__symbol":4}},{"reference":{"__symbol":5}}],"providers":[{"provider":{"token":{"identifier":{"reference":{"__symbol":6}}},"useClass":{"reference":{"__symbol":7},"diDeps":[{"isAttribute":false,"isHost":false,"isSelf":false,"isSkipSelf":false,"isOptional":false,"token":{"identifier":{"reference":{"__symbol":8}}}}],"lifecycleHooks":[]},"useFactory":null,"useExisting":null,"deps":[{"isAttribute":false,"isHost":false,"isSelf":false,"isSkipSelf":false,"isOptional":false,"token":{"identifier":{"reference":{"__symbol":8}}}}],"multi":false},"module":{"reference":{"__symbol":9},"diDeps":[],"lifecycleHooks":[]}},{"provider":{"token":{"identifier":{"reference":{"__symbol":10},"diDeps":[{"isAttribute":false,"isHost":false,"isSelf":false,"isSkipSelf":false,"isOptional":false,"token":{"identifier":{"reference":{"__symbol":11}}}},{"isAttribute":false,"isHost":false,"isSelf":false,"isSkipSelf":false,"isOptional":false,"token":{"identifier":{"reference":{"__symbol":12}}}},{"isAttribute":false,"isHost":false,"isSelf":false,"isSkipSelf":false,"isOptional":false,"token":{"identifier":{"reference":{"__symbol":13}}}},{"isAttribute":false,"isHost":false,"isSelf":false,"isSkipSelf":false,"isOptional":false,"token":{"identifier":{"reference":{"__symbol":14}}}},{"isAttribute":false,"isHost":false,"isSelf":false,"isSkipSelf":false,"isOptional":false,"token":{"identifier":{"reference":{"__symbol":15}}}},{"isAttribute":false,"isHost":false,"isSelf":false,"isSkipSelf":false,"isOptional":false,"token":{"identifier":{"reference":{"__symbol":16}}}},{"isAttribute":false,"isHost":false,"isSelf":false,"isSkipSelf":false,"isOptional":true,"token":{"identifier":{"reference":{"__symbol":17}}}},{"isAttribute":false,"isHost":false,"isSelf":false,"isSkipSelf":false,"isOptional":true,"token":{"identifier":{"reference":{"__symbol":18}}}}],"lifecycleHooks":[1]}},"useClass":{"reference":{"__symbol":10},"diDeps":[{"isAttribute":false,"isHost":false,"isSelf":false,"isSkipSelf":false,"isOptional":false,"token":{"identifier":{"reference":{"__symbol":11}}}},{"isAttribute":false,"isHost":false,"isSelf":false,"isSkipSelf":false,"isOptional":false,"token":{"identifier":{"reference":{"__symbol":12}}}},{"isAttribute":false,"isHost":false,"isSelf":false,"isSkipSelf":false,"isOptional":false,"token":{"identifier":{"reference":{"__symbol":13}}}},{"isAttribute":false,"isHost":false,"isSelf":false,"isSkipSelf":false,"isOptional":false,"token":{"identifier":{"reference":{"__symbol":14}}}},{"isAttribute":false,"isHost":false,"isSelf":false,"isSkipSelf":false,"isOptional":false,"token":{"identifier":{"reference":{"__symbol":15}}}},{"isAttribute":false,"isHost":false,"isSelf":false,"isSkipSelf":false,"isOptional":false,"token":{"identifier":{"reference":{"__symbol":16}}}},{"isAttribute":false,"isHost":false,"isSelf":false,"isSkipSelf":false,"isOptional":true,"token":{"identifier":{"reference":{"__symbol":17}}}},{"isAttribute":false,"isHost":false,"isSelf":false,"isSkipSelf":false,"isOptional":true,"token":{"identifier":{"reference":{"__symbol":18}}}}],"lifecycleHooks":[1]},"useFactory":null,"useExisting":null,"deps":[{"isAttribute":false,"isHost":false,"isSelf":false,"isSkipSelf":false,"isOptional":false,"token":{"identifier":{"reference":{"__symbol":11}}}},{"isAttribute":false,"isHost":false,"isSelf":false,"isSkipSelf":false,"isOptional":false,"token":{"identifier":{"reference":{"__symbol":12}}}},{"isAttribute":false,"isHost":false,"isSelf":false,"isSkipSelf":false,"isOptional":false,"token":{"identifier":{"reference":{"__symbol":13}}}},{"isAttribute":false,"isHost":false,"isSelf":false,"isSkipSelf":false,"isOptional":false,"token":{"identifier":{"reference":{"__symbol":14}}}},{"isAttribute":false,"isHost":false,"isSelf":false,"isSkipSelf":false,"isOptional":false,"token":{"identifier":{"reference":{"__symbol":15}}}},{"isAttribute":false,"isHost":false,"isSelf":false,"isSkipSelf":false,"isOptional":false,"token":{"identifier":{"reference":{"__symbol":16}}}},{"isAttribute":false,"isHost":false,"isSelf":false,"isSkipSelf":false,"isOptional":true,"token":{"identifier":{"reference":{"__symbol":17}}}},{"isAttribute":false,"isHost":false,"isSelf":false,"isSkipSelf":false,"isOptional":true,"token":{"identifier":{"reference":{"__symbol":18}}}}],"multi":false},"module":{"reference":{"__symbol":19},"diDeps":[],"lifecycleHooks":[]}},{"provider":{"token":{"identifier":{"reference":{"__symbol":20}}},"useClass":null,"useFactory":null,"useExisting":{"identifier":{"reference":{"__symbol":10}}},"multi":false},"module":{"reference":{"__symbol":19},"diDeps":[],"lifecycleHooks":[]}},{"provider":{"token":{"identifier":{"reference":{"__symbol":16},"diDeps":[{"isAttribute":false,"isHost":false,"isSelf":false,"isSkipSelf":false,"isOptional":true,"token":{"identifier":{"reference":{"__symbol":21}}}}],"lifecycleHooks":[]}},"useClass":{"reference":{"__symbol":16},"diDeps":[{"isAttribute":false,"isHost":false,"isSelf":false,"isSkipSelf":false,"isOptional":true,"token":{"identifier":{"reference":{"__symbol":21}}}}],"lifecycleHooks":[]},"useFactory":null,"useExisting":null,"deps":[{"isAttribute":false,"isHost":false,"isSelf":false,"isSkipSelf":false,"isOptional":true,"token":{"identifier":{"reference":{"__symbol":21}}}}],"multi":false},"module":{"reference":{"__symbol":19},"diDeps":[],"lifecycleHooks":[]}},{"provider":{"token":{"identifier":{"reference":{"__symbol":22},"diDeps":[],"lifecycleHooks":[]}},"useClass":{"reference":{"__symbol":22},"diDeps":[],"lifecycleHooks":[]},"useFactory":null,"useExisting":null,"deps":[],"multi":false},"module":{"reference":{"__symbol":19},"diDeps":[],"lifecycleHooks":[]}},{"provider":{"token":{"identifier":{"reference":{"__symbol":23}}},"useClass":null,"useFactory":{"reference":{"__symbol":24},"diDeps":[]},"useExisting":null,"deps":[],"multi":false},"module":{"reference":{"__symbol":19},"diDeps":[],"lifecycleHooks":[]}},{"provider":{"token":{"identifier":{"reference":{"__symbol":25},"diDeps":[{"isAttribute":false,"isHost":false,"isSelf":false,"isSkipSelf":false,"isOptional":false,"token":{"identifier":{"reference":{"__symbol":26}}}},{"isAttribute":false,"isHost":false,"isSelf":false,"isSkipSelf":false,"isOptional":false,"token":{"identifier":{"reference":{"__symbol":27}}}},{"isAttribute":false,"isHost":false,"isSelf":false,"isSkipSelf":false,"isOptional":false,"token":{"identifier":{"reference":{"__symbol":28}}}}],"lifecycleHooks":[]}},"useClass":{"reference":{"__symbol":25},"diDeps":[{"isAttribute":false,"isHost":false,"isSelf":false,"isSkipSelf":false,"isOptional":false,"token":{"identifier":{"reference":{"__symbol":26}}}},{"isAttribute":false,"isHost":false,"isSelf":false,"isSkipSelf":false,"isOptional":false,"token":{"identifier":{"reference":{"__symbol":27}}}},{"isAttribute":false,"isHost":false,"isSelf":false,"isSkipSelf":false,"isOptional":false,"token":{"identifier":{"reference":{"__symbol":28}}}}],"lifecycleHooks":[]},"useFactory":null,"useExisting":null,"deps":[{"isAttribute":false,"isHost":false,"isSelf":false,"isSkipSelf":false,"isOptional":false,"token":{"identifier":{"reference":{"__symbol":26}}}},{"isAttribute":false,"isHost":false,"isSelf":false,"isSkipSelf":false,"isOptional":false,"token":{"identifier":{"reference":{"__symbol":27}}}},{"isAttribute":false,"isHost":false,"isSelf":false,"isSkipSelf":false,"isOptional":false,"token":{"identifier":{"reference":{"__symbol":28}}}}],"multi":false},"module":{"reference":{"__symbol":19},"diDeps":[],"lifecycleHooks":[]}},{"provider":{"token":{"identifier":{"reference":{"__symbol":28},"diDeps":[{"isAttribute":false,"isHost":false,"isSelf":false,"isSkipSelf":false,"isOptional":false,"token":{"identifier":{"reference":{"__symbol":11}}}}],"lifecycleHooks":[]}},"useClass":{"reference":{"__symbol":28},"diDeps":[{"isAttribute":false,"isHost":false,"isSelf":false,"isSkipSelf":false,"isOptional":false,"token":{"identifier":{"reference":{"__symbol":11}}}}],"lifecycleHooks":[]},"useFactory":null,"useExisting":null,"deps":[{"isAttribute":false,"isHost":false,"isSelf":false,"isSkipSelf":false,"isOptional":false,"token":{"identifier":{"reference":{"__symbol":11}}}}],"multi":false},"module":{"reference":{"__symbol":19},"diDeps":[],"lifecycleHooks":[]}},{"provider":{"token":{"identifier":{"reference":{"__symbol":29}}},"useClass":null,"useFactory":{"reference":{"__symbol":30},"diDeps":[]},"useExisting":null,"deps":[],"multi":false},"module":{"reference":{"__symbol":19},"diDeps":[],"lifecycleHooks":[]}},{"provider":{"token":{"identifier":{"reference":{"__symbol":31}}},"useClass":null,"useFactory":{"reference":{"__symbol":32},"diDeps":[]},"useExisting":null,"deps":[],"multi":false},"module":{"reference":{"__symbol":19},"diDeps":[],"lifecycleHooks":[]}},{"provider":{"token":{"identifier":{"reference":{"__symbol":8}}},"useClass":null,"useFactory":{"reference":{"__symbol":33},"diDeps":[{"isAttribute":false,"isHost":false,"isSelf":false,"isSkipSelf":true,"isOptional":true,"token":{"identifier":{"reference":{"__symbol":8}}}}]},"useExisting":null,"deps":[{"isAttribute":false,"isHost":false,"isSelf":false,"isSkipSelf":true,"isOptional":true,"token":{"identifier":{"reference":{"__symbol":8}}}}],"multi":false},"module":{"reference":{"__symbol":19},"diDeps":[],"lifecycleHooks":[]}},{"provider":{"token":{"identifier":{"reference":{"__symbol":27}}},"useClass":null,"useFactory":null,"useExisting":{"identifier":{"reference":{"__symbol":34}}},"multi":false},"module":{"reference":{"__symbol":35},"diDeps":[{"isAttribute":false,"isHost":false,"isSelf":false,"isSkipSelf":true,"isOptional":true,"token":{"identifier":{"reference":{"__symbol":35}}}}],"lifecycleHooks":[]}},{"provider":{"token":{"identifier":{"reference":{"__symbol":34}}},"useClass":{"reference":{"__symbol":36},"diDeps":[],"lifecycleHooks":[]},"useFactory":null,"useExisting":null,"deps":[],"multi":false},"module":{"reference":{"__symbol":35},"diDeps":[{"isAttribute":false,"isHost":false,"isSelf":false,"isSkipSelf":true,"isOptional":true,"token":{"identifier":{"reference":{"__symbol":35}}}}],"lifecycleHooks":[]}},{"provider":{"token":{"identifier":{"reference":{"__symbol":14}}},"useClass":null,"useFactory":{"reference":{"__symbol":37},"diDeps":[]},"useExisting":null,"deps":[],"multi":false},"module":{"reference":{"__symbol":35},"diDeps":[{"isAttribute":false,"isHost":false,"isSelf":false,"isSkipSelf":true,"isOptional":true,"token":{"identifier":{"reference":{"__symbol":35}}}}],"lifecycleHooks":[]}},{"provider":{"token":{"identifier":{"reference":{"__symbol":38}}},"useClass":null,"useFactory":{"reference":{"__symbol":39},"diDeps":[]},"useExisting":null,"deps":[],"multi":false},"module":{"reference":{"__symbol":35},"diDeps":[{"isAttribute":false,"isHost":false,"isSelf":false,"isSkipSelf":true,"isOptional":true,"token":{"identifier":{"reference":{"__symbol":35}}}}],"lifecycleHooks":[]}},{"provider":{"token":{"identifier":{"reference":{"__symbol":40}}},"useClass":{"reference":{"__symbol":41},"diDeps":[],"lifecycleHooks":[]},"useFactory":null,"useExisting":null,"deps":[],"multi":true},"module":{"reference":{"__symbol":35},"diDeps":[{"isAttribute":false,"isHost":false,"isSelf":false,"isSkipSelf":true,"isOptional":true,"token":{"identifier":{"reference":{"__symbol":35}}}}],"lifecycleHooks":[]}},{"provider":{"token":{"identifier":{"reference":{"__symbol":40}}},"useClass":{"reference":{"__symbol":42},"diDeps":[],"lifecycleHooks":[]},"useFactory":null,"useExisting":null,"deps":[],"multi":true},"module":{"reference":{"__symbol":35},"diDeps":[{"isAttribute":false,"isHost":false,"isSelf":false,"isSkipSelf":true,"isOptional":true,"token":{"identifier":{"reference":{"__symbol":35}}}}],"lifecycleHooks":[]}},{"provider":{"token":{"identifier":{"reference":{"__symbol":40}}},"useClass":{"reference":{"__symbol":43},"diDeps":[{"isAttribute":false,"isHost":false,"isSelf":false,"isSkipSelf":false,"isOptional":false,"token":{"identifier":{"reference":{"__symbol":44}}}}],"lifecycleHooks":[]},"useFactory":null,"useExisting":null,"deps":[{"isAttribute":false,"isHost":false,"isSelf":false,"isSkipSelf":false,"isOptional":false,"token":{"identifier":{"reference":{"__symbol":44}}}}],"multi":true},"module":{"reference":{"__symbol":35},"diDeps":[{"isAttribute":false,"isHost":false,"isSelf":false,"isSkipSelf":true,"isOptional":true,"token":{"identifier":{"reference":{"__symbol":35}}}}],"lifecycleHooks":[]}},{"provider":{"token":{"identifier":{"reference":{"__symbol":44}}},"useClass":{"reference":{"__symbol":45},"diDeps":[],"lifecycleHooks":[]},"useFactory":null,"useExisting":null,"deps":[],"multi":false},"module":{"reference":{"__symbol":35},"diDeps":[{"isAttribute":false,"isHost":false,"isSelf":false,"isSkipSelf":true,"isOptional":true,"token":{"identifier":{"reference":{"__symbol":35}}}}],"lifecycleHooks":[]}},{"provider":{"token":{"identifier":{"reference":{"__symbol":46}}},"useClass":{"reference":{"__symbol":47},"diDeps":[{"isAttribute":false,"isHost":false,"isSelf":false,"isSkipSelf":false,"isOptional":false,"token":{"identifier":{"reference":{"__symbol":38}}}},{"isAttribute":false,"isHost":false,"isSelf":false,"isSkipSelf":false,"isOptional":false,"token":{"identifier":{"reference":{"__symbol":48}}}},{"isAttribute":false,"isHost":false,"isSelf":false,"isSkipSelf":false,"isOptional":false,"token":{"identifier":{"reference":{"__symbol":49}}}},{"isAttribute":false,"isHost":false,"isSelf":false,"isSkipSelf":false,"isOptional":false,"token":{"identifier":{"reference":{"__symbol":50}}}},{"isAttribute":false,"isHost":false,"isSelf":false,"isSkipSelf":false,"isOptional":false,"token":{"identifier":{"reference":{"__symbol":23}}}}],"lifecycleHooks":[]},"useFactory":null,"useExisting":null,"deps":[{"isAttribute":false,"isHost":false,"isSelf":false,"isSkipSelf":false,"isOptional":false,"token":{"identifier":{"reference":{"__symbol":38}}}},{"isAttribute":false,"isHost":false,"isSelf":false,"isSkipSelf":false,"isOptional":false,"token":{"identifier":{"reference":{"__symbol":48}}}},{"isAttribute":false,"isHost":false,"isSelf":false,"isSkipSelf":false,"isOptional":false,"token":{"identifier":{"reference":{"__symbol":49}}}},{"isAttribute":false,"isHost":false,"isSelf":false,"isSkipSelf":false,"isOptional":false,"token":{"identifier":{"reference":{"__symbol":50}}}},{"isAttribute":false,"isHost":false,"isSelf":false,"isSkipSelf":false,"isOptional":false,"token":{"identifier":{"reference":{"__symbol":23}}}}],"multi":false},"module":{"reference":{"__symbol":35},"diDeps":[{"isAttribute":false,"isHost":false,"isSelf":false,"isSkipSelf":true,"isOptional":true,"token":{"identifier":{"reference":{"__symbol":35}}}}],"lifecycleHooks":[]}},{"provider":{"token":{"identifier":{"reference":{"__symbol":26}}},"useClass":null,"useFactory":null,"useExisting":{"identifier":{"reference":{"__symbol":46}}},"multi":false},"module":{"reference":{"__symbol":35},"diDeps":[{"isAttribute":false,"isHost":false,"isSelf":false,"isSkipSelf":true,"isOptional":true,"token":{"identifier":{"reference":{"__symbol":35}}}}],"lifecycleHooks":[]}},{"provider":{"token":{"identifier":{"reference":{"__symbol":51}}},"useClass":null,"useFactory":null,"useExisting":{"identifier":{"reference":{"__symbol":49}}},"multi":false},"module":{"reference":{"__symbol":35},"diDeps":[{"isAttribute":false,"isHost":false,"isSelf":false,"isSkipSelf":true,"isOptional":true,"token":{"identifier":{"reference":{"__symbol":35}}}}],"lifecycleHooks":[]}},{"provider":{"token":{"identifier":{"reference":{"__symbol":50}}},"useClass":null,"useFactory":{"reference":{"__symbol":52},"diDeps":[]},"useExisting":null,"deps":[],"multi":false},"module":{"reference":{"__symbol":35},"diDeps":[{"isAttribute":false,"isHost":false,"isSelf":false,"isSkipSelf":true,"isOptional":true,"token":{"identifier":{"reference":{"__symbol":35}}}}],"lifecycleHooks":[]}},{"provider":{"token":{"identifier":{"reference":{"__symbol":49},"diDeps":[{"isAttribute":false,"isHost":false,"isSelf":false,"isSkipSelf":false,"isOptional":false,"token":{"identifier":{"reference":{"__symbol":38}}}}],"lifecycleHooks":[1]}},"useClass":{"reference":{"__symbol":49},"diDeps":[{"isAttribute":false,"isHost":false,"isSelf":false,"isSkipSelf":false,"isOptional":false,"token":{"identifier":{"reference":{"__symbol":38}}}}],"lifecycleHooks":[1]},"useFactory":null,"useExisting":null,"deps":[{"isAttribute":false,"isHost":false,"isSelf":false,"isSkipSelf":false,"isOptional":false,"token":{"identifier":{"reference":{"__symbol":38}}}}],"multi":false},"module":{"reference":{"__symbol":35},"diDeps":[{"isAttribute":false,"isHost":false,"isSelf":false,"isSkipSelf":true,"isOptional":true,"token":{"identifier":{"reference":{"__symbol":35}}}}],"lifecycleHooks":[]}},{"provider":{"token":{"identifier":{"reference":{"__symbol":18},"diDeps":[{"isAttribute":false,"isHost":false,"isSelf":false,"isSkipSelf":false,"isOptional":false,"token":{"identifier":{"reference":{"__symbol":11}}}}],"lifecycleHooks":[]}},"useClass":{"reference":{"__symbol":18},"diDeps":[{"isAttribute":false,"isHost":false,"isSelf":false,"isSkipSelf":false,"isOptional":false,"token":{"identifier":{"reference":{"__symbol":11}}}}],"lifecycleHooks":[]},"useFactory":null,"useExisting":null,"deps":[{"isAttribute":false,"isHost":false,"isSelf":false,"isSkipSelf":false,"isOptional":false,"token":{"identifier":{"reference":{"__symbol":11}}}}],"multi":false},"module":{"reference":{"__symbol":35},"diDeps":[{"isAttribute":false,"isHost":false,"isSelf":false,"isSkipSelf":true,"isOptional":true,"token":{"identifier":{"reference":{"__symbol":35}}}}],"lifecycleHooks":[]}},{"provider":{"token":{"identifier":{"reference":{"__symbol":48},"diDeps":[{"isAttribute":false,"isHost":false,"isSelf":false,"isSkipSelf":false,"isOptional":false,"token":{"identifier":{"reference":{"__symbol":40}}}},{"isAttribute":false,"isHost":false,"isSelf":false,"isSkipSelf":false,"isOptional":false,"token":{"identifier":{"reference":{"__symbol":11}}}}],"lifecycleHooks":[]}},"useClass":{"reference":{"__symbol":48},"diDeps":[{"isAttribute":false,"isHost":false,"isSelf":false,"isSkipSelf":false,"isOptional":false,"token":{"identifier":{"reference":{"__symbol":40}}}},{"isAttribute":false,"isHost":false,"isSelf":false,"isSkipSelf":false,"isOptional":false,"token":{"identifier":{"reference":{"__symbol":11}}}}],"lifecycleHooks":[]},"useFactory":null,"useExisting":null,"deps":[{"isAttribute":false,"isHost":false,"isSelf":false,"isSkipSelf":false,"isOptional":false,"token":{"identifier":{"reference":{"__symbol":40}}}},{"isAttribute":false,"isHost":false,"isSelf":false,"isSkipSelf":false,"isOptional":false,"token":{"identifier":{"reference":{"__symbol":11}}}}],"multi":false},"module":{"reference":{"__symbol":35},"diDeps":[{"isAttribute":false,"isHost":false,"isSelf":false,"isSkipSelf":true,"isOptional":true,"token":{"identifier":{"reference":{"__symbol":35}}}}],"lifecycleHooks":[]}},{"provider":{"token":{"identifier":{"reference":{"__symbol":26}}},"useClass":null,"useFactory":{"reference":{"__symbol":53},"diDeps":[{"isAttribute":false,"isHost":false,"isSelf":false,"isSkipSelf":false,"isOptional":false,"token":{"identifier":{"reference":{"__symbol":46}}}},{"isAttribute":false,"isHost":false,"isSelf":false,"isSkipSelf":false,"isOptional":true,"token":{"identifier":{"reference":{"__symbol":54}}}},{"isAttribute":false,"isHost":false,"isSelf":false,"isSkipSelf":false,"isOptional":true,"token":{"identifier":{"reference":{"__symbol":55}}}}]},"useExisting":null,"deps":[{"isAttribute":false,"isHost":false,"isSelf":false,"isSkipSelf":false,"isOptional":false,"token":{"identifier":{"reference":{"__symbol":46}}}},{"isAttribute":false,"isHost":false,"isSelf":false,"isSkipSelf":false,"isOptional":true,"token":{"identifier":{"reference":{"__symbol":54}}}},{"isAttribute":false,"isHost":false,"isSelf":false,"isSkipSelf":false,"isOptional":true,"token":{"identifier":{"reference":{"__symbol":55}}}}],"multi":false},"module":{"reference":{"__symbol":35},"diDeps":[{"isAttribute":false,"isHost":false,"isSelf":false,"isSkipSelf":true,"isOptional":true,"token":{"identifier":{"reference":{"__symbol":35}}}}],"lifecycleHooks":[]}},{"provider":{"token":{"identifier":{"reference":{"__symbol":56},"diDeps":[],"lifecycleHooks":[]}},"useClass":{"reference":{"__symbol":56},"diDeps":[],"lifecycleHooks":[]},"useFactory":null,"useExisting":null,"deps":[],"multi":false},"module":{"reference":{"__symbol":35},"diDeps":[{"isAttribute":false,"isHost":false,"isSelf":false,"isSkipSelf":true,"isOptional":true,"token":{"identifier":{"reference":{"__symbol":35}}}}],"lifecycleHooks":[]}},{"provider":{"token":{"identifier":{"reference":{"__symbol":57},"diDeps":[],"lifecycleHooks":[]}},"useClass":{"reference":{"__symbol":57},"diDeps":[],"lifecycleHooks":[]},"useFactory":null,"useExisting":null,"deps":[],"multi":false},"module":{"reference":{"__symbol":58},"diDeps":[],"lifecycleHooks":[]}},{"provider":{"token":{"identifier":{"reference":{"__symbol":59},"diDeps":[],"lifecycleHooks":[]}},"useClass":{"reference":{"__symbol":59},"diDeps":[],"lifecycleHooks":[]},"useFactory":null,"useExisting":null,"deps":[],"multi":false},"module":{"reference":{"__symbol":58},"diDeps":[],"lifecycleHooks":[]}},{"provider":{"token":{"identifier":{"reference":{"__symbol":60}}},"useClass":null,"useFactory":{"reference":{"__symbol":61},"diDeps":[{"isAttribute":false,"isHost":false,"isSelf":false,"isSkipSelf":false,"isOptional":false,"token":{"identifier":{"reference":{"__symbol":62}}}},{"isAttribute":false,"isHost":false,"isSelf":false,"isSkipSelf":false,"isOptional":false,"token":{"identifier":{"reference":{"__symbol":63}}}}]},"useExisting":null,"deps":[{"isAttribute":false,"isHost":false,"isSelf":false,"isSkipSelf":false,"isOptional":false,"token":{"identifier":{"reference":{"__symbol":62}}}},{"isAttribute":false,"isHost":false,"isSelf":false,"isSkipSelf":false,"isOptional":false,"token":{"identifier":{"reference":{"__symbol":63}}}}],"multi":false},"module":{"reference":{"__symbol":64},"diDeps":[],"lifecycleHooks":[]}},{"provider":{"token":{"identifier":{"reference":{"__symbol":65},"diDeps":[],"lifecycleHooks":[]}},"useClass":{"reference":{"__symbol":65},"diDeps":[],"lifecycleHooks":[]},"useFactory":null,"useExisting":null,"deps":[],"multi":false},"module":{"reference":{"__symbol":64},"diDeps":[],"lifecycleHooks":[]}},{"provider":{"token":{"identifier":{"reference":{"__symbol":63}}},"useClass":{"reference":{"__symbol":66},"diDeps":[],"lifecycleHooks":[]},"useFactory":null,"useExisting":null,"deps":[],"multi":false},"module":{"reference":{"__symbol":64},"diDeps":[],"lifecycleHooks":[]}},{"provider":{"token":{"identifier":{"reference":{"__symbol":67}}},"useClass":{"reference":{"__symbol":68},"diDeps":[],"lifecycleHooks":[]},"useFactory":null,"useExisting":null,"deps":[],"multi":false},"module":{"reference":{"__symbol":64},"diDeps":[],"lifecycleHooks":[]}},{"provider":{"token":{"identifier":{"reference":{"__symbol":62},"diDeps":[{"isAttribute":false,"isHost":false,"isSelf":false,"isSkipSelf":false,"isOptional":false,"token":{"identifier":{"reference":{"__symbol":65}}}},{"isAttribute":false,"isHost":false,"isSelf":false,"isSkipSelf":false,"isOptional":false,"token":{"identifier":{"reference":{"__symbol":67}}}},{"isAttribute":false,"isHost":false,"isSelf":false,"isSkipSelf":false,"isOptional":false,"token":{"identifier":{"reference":{"__symbol":69}}}}],"lifecycleHooks":[]}},"useClass":{"reference":{"__symbol":62},"diDeps":[{"isAttribute":false,"isHost":false,"isSelf":false,"isSkipSelf":false,"isOptional":false,"token":{"identifier":{"reference":{"__symbol":65}}}},{"isAttribute":false,"isHost":false,"isSelf":false,"isSkipSelf":false,"isOptional":false,"token":{"identifier":{"reference":{"__symbol":67}}}},{"isAttribute":false,"isHost":false,"isSelf":false,"isSkipSelf":false,"isOptional":false,"token":{"identifier":{"reference":{"__symbol":69}}}}],"lifecycleHooks":[]},"useFactory":null,"useExisting":null,"deps":[{"isAttribute":false,"isHost":false,"isSelf":false,"isSkipSelf":false,"isOptional":false,"token":{"identifier":{"reference":{"__symbol":65}}}},{"isAttribute":false,"isHost":false,"isSelf":false,"isSkipSelf":false,"isOptional":false,"token":{"identifier":{"reference":{"__symbol":67}}}},{"isAttribute":false,"isHost":false,"isSelf":false,"isSkipSelf":false,"isOptional":false,"token":{"identifier":{"reference":{"__symbol":69}}}}],"multi":false},"module":{"reference":{"__symbol":64},"diDeps":[],"lifecycleHooks":[]}},{"provider":{"token":{"identifier":{"reference":{"__symbol":69}}},"useClass":null,"useFactory":{"reference":{"__symbol":70},"diDeps":[]},"useExisting":null,"deps":[],"multi":false},"module":{"reference":{"__symbol":64},"diDeps":[],"lifecycleHooks":[]}},{"provider":{"token":{"identifier":{"reference":{"__symbol":71},"diDeps":[{"isAttribute":false,"isHost":false,"isSelf":false,"isSkipSelf":false,"isOptional":false,"token":{"identifier":{"reference":{"__symbol":72}}}}],"lifecycleHooks":[]}},"useClass":{"reference":{"__symbol":71},"diDeps":[{"isAttribute":false,"isHost":false,"isSelf":false,"isSkipSelf":false,"isOptional":false,"token":{"identifier":{"reference":{"__symbol":72}}}}],"lifecycleHooks":[]},"useFactory":null,"useExisting":null,"deps":[{"isAttribute":false,"isHost":false,"isSelf":false,"isSkipSelf":false,"isOptional":false,"token":{"identifier":{"reference":{"__symbol":72}}}}],"multi":false},"module":{"reference":{"__symbol":2},"diDeps":[],"lifecycleHooks":[]}},{"provider":{"token":{"identifier":{"reference":{"__symbol":73}}},"useClass":{"reference":{"__symbol":74},"diDeps":[],"lifecycleHooks":[]},"useFactory":null,"useExisting":null,"deps":[],"multi":false},"module":{"reference":{"__symbol":2},"diDeps":[],"lifecycleHooks":[]}},{"provider":{"token":{"identifier":{"reference":{"__symbol":75}}},"useClass":null,"useFactory":{"reference":{"__symbol":76},"diDeps":[{"isAttribute":false,"isHost":false,"isSelf":false,"isSkipSelf":false,"isOptional":false,"token":{"identifier":{"reference":{"__symbol":20}}}},{"isAttribute":false,"isHost":false,"isSelf":false,"isSkipSelf":false,"isOptional":false,"token":{"identifier":{"reference":{"__symbol":73}}}},{"isAttribute":false,"isHost":false,"isSelf":false,"isSkipSelf":false,"isOptional":false,"token":{"identifier":{"reference":{"__symbol":77}}}},{"isAttribute":false,"isHost":false,"isSelf":false,"isSkipSelf":false,"isOptional":false,"token":{"identifier":{"reference":{"__symbol":71}}}},{"isAttribute":false,"isHost":false,"isSelf":false,"isSkipSelf":false,"isOptional":false,"token":{"identifier":{"reference":{"__symbol":13}}}},{"isAttribute":false,"isHost":false,"isSelf":false,"isSkipSelf":false,"isOptional":false,"token":{"identifier":{"reference":{"__symbol":78}}}},{"isAttribute":false,"isHost":false,"isSelf":false,"isSkipSelf":false,"isOptional":false,"token":{"identifier":{"reference":{"__symbol":22}}}},{"isAttribute":false,"isHost":false,"isSelf":false,"isSkipSelf":false,"isOptional":false,"token":{"identifier":{"reference":{"__symbol":79}}}},{"isAttribute":false,"isHost":false,"isSelf":false,"isSkipSelf":false,"isOptional":false,"token":{"identifier":{"reference":{"__symbol":80}}}},{"isAttribute":false,"isHost":false,"isSelf":false,"isSkipSelf":false,"isOptional":true,"token":{"identifier":{"reference":{"__symbol":81}}}},{"isAttribute":false,"isHost":false,"isSelf":false,"isSkipSelf":false,"isOptional":true,"token":{"identifier":{"reference":{"__symbol":82}}}}]},"useExisting":null,"deps":[{"isAttribute":false,"isHost":false,"isSelf":false,"isSkipSelf":false,"isOptional":false,"token":{"identifier":{"reference":{"__symbol":20}}}},{"isAttribute":false,"isHost":false,"isSelf":false,"isSkipSelf":false,"isOptional":false,"token":{"identifier":{"reference":{"__symbol":73}}}},{"isAttribute":false,"isHost":false,"isSelf":false,"isSkipSelf":false,"isOptional":false,"token":{"identifier":{"reference":{"__symbol":77}}}},{"isAttribute":false,"isHost":false,"isSelf":false,"isSkipSelf":false,"isOptional":false,"token":{"identifier":{"reference":{"__symbol":71}}}},{"isAttribute":false,"isHost":false,"isSelf":false,"isSkipSelf":false,"isOptional":false,"token":{"identifier":{"reference":{"__symbol":13}}}},{"isAttribute":false,"isHost":false,"isSelf":false,"isSkipSelf":false,"isOptional":false,"token":{"identifier":{"reference":{"__symbol":78}}}},{"isAttribute":false,"isHost":false,"isSelf":false,"isSkipSelf":false,"isOptional":false,"token":{"identifier":{"reference":{"__symbol":22}}}},{"isAttribute":false,"isHost":false,"isSelf":false,"isSkipSelf":false,"isOptional":false,"token":{"identifier":{"reference":{"__symbol":79}}}},{"isAttribute":false,"isHost":false,"isSelf":false,"isSkipSelf":false,"isOptional":false,"token":{"identifier":{"reference":{"__symbol":80}}}},{"isAttribute":false,"isHost":false,"isSelf":false,"isSkipSelf":false,"isOptional":true,"token":{"identifier":{"reference":{"__symbol":81}}}},{"isAttribute":false,"isHost":false,"isSelf":false,"isSkipSelf":false,"isOptional":true,"token":{"identifier":{"reference":{"__symbol":82}}}}],"multi":false},"module":{"reference":{"__symbol":2},"diDeps":[],"lifecycleHooks":[]}},{"provider":{"token":{"identifier":{"reference":{"__symbol":77},"diDeps":[],"lifecycleHooks":[]}},"useClass":{"reference":{"__symbol":77},"diDeps":[],"lifecycleHooks":[]},"useFactory":null,"useExisting":null,"deps":[],"multi":false},"module":{"reference":{"__symbol":2},"diDeps":[],"lifecycleHooks":[]}},{"provider":{"token":{"identifier":{"reference":{"__symbol":83}}},"useClass":null,"useFactory":{"reference":{"__symbol":84},"diDeps":[{"isAttribute":false,"isHost":false,"isSelf":false,"isSkipSelf":false,"isOptional":false,"token":{"identifier":{"reference":{"__symbol":75}}}}]},"useExisting":null,"deps":[{"isAttribute":false,"isHost":false,"isSelf":false,"isSkipSelf":false,"isOptional":false,"token":{"identifier":{"reference":{"__symbol":75}}}}],"multi":false},"module":{"reference":{"__symbol":2},"diDeps":[],"lifecycleHooks":[]}},{"provider":{"token":{"identifier":{"reference":{"__symbol":78}}},"useClass":{"reference":{"__symbol":85},"diDeps":[{"isAttribute":false,"isHost":false,"isSelf":false,"isSkipSelf":false,"isOptional":false,"token":{"identifier":{"reference":{"__symbol":22}}}},{"isAttribute":false,"isHost":false,"isSelf":false,"isSkipSelf":false,"isOptional":true,"token":{"identifier":{"reference":{"__symbol":86}}}}],"lifecycleHooks":[]},"useFactory":null,"useExisting":null,"deps":[{"isAttribute":false,"isHost":false,"isSelf":false,"isSkipSelf":false,"isOptional":false,"token":{"identifier":{"reference":{"__symbol":22}}}},{"isAttribute":false,"isHost":false,"isSelf":false,"isSkipSelf":false,"isOptional":true,"token":{"identifier":{"reference":{"__symbol":86}}}}],"multi":false},"module":{"reference":{"__symbol":2},"diDeps":[],"lifecycleHooks":[]}},{"provider":{"token":{"identifier":{"reference":{"__symbol":87},"diDeps":[{"isAttribute":false,"isHost":false,"isSelf":false,"isSkipSelf":false,"isOptional":false,"token":{"identifier":{"reference":{"__symbol":75}}}},{"isAttribute":false,"isHost":false,"isSelf":false,"isSkipSelf":false,"isOptional":false,"token":{"identifier":{"reference":{"__symbol":78}}}},{"isAttribute":false,"isHost":false,"isSelf":false,"isSkipSelf":false,"isOptional":false,"token":{"identifier":{"reference":{"__symbol":22}}}},{"isAttribute":false,"isHost":false,"isSelf":false,"isSkipSelf":false,"isOptional":false,"token":{"identifier":{"reference":{"__symbol":13}}}},{"isAttribute":false,"isHost":false,"isSelf":false,"isSkipSelf":false,"isOptional":false,"token":{"identifier":{"reference":{"__symbol":88}}}}],"lifecycleHooks":[1]}},"useClass":{"reference":{"__symbol":87},"diDeps":[{"isAttribute":false,"isHost":false,"isSelf":false,"isSkipSelf":false,"isOptional":false,"token":{"identifier":{"reference":{"__symbol":75}}}},{"isAttribute":false,"isHost":false,"isSelf":false,"isSkipSelf":false,"isOptional":false,"token":{"identifier":{"reference":{"__symbol":78}}}},{"isAttribute":false,"isHost":false,"isSelf":false,"isSkipSelf":false,"isOptional":false,"token":{"identifier":{"reference":{"__symbol":22}}}},{"isAttribute":false,"isHost":false,"isSelf":false,"isSkipSelf":false,"isOptional":false,"token":{"identifier":{"reference":{"__symbol":13}}}},{"isAttribute":false,"isHost":false,"isSelf":false,"isSkipSelf":false,"isOptional":false,"token":{"identifier":{"reference":{"__symbol":88}}}}],"lifecycleHooks":[1]},"useFactory":null,"useExisting":null,"deps":[{"isAttribute":false,"isHost":false,"isSelf":false,"isSkipSelf":false,"isOptional":false,"token":{"identifier":{"reference":{"__symbol":75}}}},{"isAttribute":false,"isHost":false,"isSelf":false,"isSkipSelf":false,"isOptional":false,"token":{"identifier":{"reference":{"__symbol":78}}}},{"isAttribute":false,"isHost":false,"isSelf":false,"isSkipSelf":false,"isOptional":false,"token":{"identifier":{"reference":{"__symbol":22}}}},{"isAttribute":false,"isHost":false,"isSelf":false,"isSkipSelf":false,"isOptional":false,"token":{"identifier":{"reference":{"__symbol":13}}}},{"isAttribute":false,"isHost":false,"isSelf":false,"isSkipSelf":false,"isOptional":false,"token":{"identifier":{"reference":{"__symbol":88}}}}],"multi":false},"module":{"reference":{"__symbol":2},"diDeps":[],"lifecycleHooks":[]}},{"provider":{"token":{"identifier":{"reference":{"__symbol":89},"diDeps":[],"lifecycleHooks":[]}},"useClass":{"reference":{"__symbol":89},"diDeps":[],"lifecycleHooks":[]},"useFactory":null,"useExisting":null,"deps":[],"multi":false},"module":{"reference":{"__symbol":2},"diDeps":[],"lifecycleHooks":[]}},{"provider":{"token":{"identifier":{"reference":{"__symbol":90},"diDeps":[],"lifecycleHooks":[]}},"useClass":{"reference":{"__symbol":90},"diDeps":[],"lifecycleHooks":[]},"useFactory":null,"useExisting":null,"deps":[],"multi":false},"module":{"reference":{"__symbol":2},"diDeps":[],"lifecycleHooks":[]}},{"provider":{"token":{"identifier":{"reference":{"__symbol":80}}},"useClass":null,"useValue":{"enableTracing":false},"useFactory":null,"useExisting":null,"multi":false},"module":{"reference":{"__symbol":2},"diDeps":[],"lifecycleHooks":[]}},{"provider":{"token":{"identifier":{"reference":{"__symbol":79}}},"useClass":null,"useValue":[{"path":"login","component":{"__symbol":3}},{"path":"","component":{"__symbol":4}}],"useFactory":null,"useExisting":null,"multi":true},"module":{"reference":{"__symbol":2},"diDeps":[],"lifecycleHooks":[]}},{"provider":{"token":{"identifier":{"reference":{"__symbol":91}}},"useClass":null,"useFactory":{"reference":{"__symbol":92},"diDeps":[{"isAttribute":false,"isHost":false,"isSelf":false,"isSkipSelf":true,"isOptional":true,"token":{"identifier":{"reference":{"__symbol":75}}}}]},"useExisting":null,"deps":[{"isAttribute":false,"isHost":false,"isSelf":false,"isSkipSelf":true,"isOptional":true,"token":{"identifier":{"reference":{"__symbol":75}}}}],"multi":false},"module":{"reference":{"__symbol":2},"diDeps":[],"lifecycleHooks":[]}},{"provider":{"token":{"identifier":{"reference":{"__symbol":80}}},"useClass":null,"useValue":{},"useFactory":null,"useExisting":null,"multi":false},"module":{"reference":{"__symbol":2},"diDeps":[],"lifecycleHooks":[]}},{"provider":{"token":{"identifier":{"reference":{"__symbol":72}}},"useClass":null,"useFactory":{"reference":{"__symbol":93},"diDeps":[{"isAttribute":false,"isHost":false,"isSelf":false,"isSkipSelf":false,"isOptional":false,"token":{"identifier":{"reference":{"__symbol":94}}}},{"isAttribute":false,"isHost":false,"isSelf":false,"isSkipSelf":false,"isOptional":true,"token":{"identifier":{"reference":{"__symbol":95}}}},{"isAttribute":false,"isHost":false,"isSelf":false,"isSkipSelf":false,"isOptional":false,"token":{"identifier":{"reference":{"__symbol":80}}}}]},"useExisting":null,"deps":[{"isAttribute":false,"isHost":false,"isSelf":false,"isSkipSelf":false,"isOptional":false,"token":{"identifier":{"reference":{"__symbol":94}}}},{"isAttribute":false,"isHost":false,"isSelf":false,"isSkipSelf":false,"isOptional":true,"token":{"identifier":{"reference":{"__symbol":95}}}},{"isAttribute":false,"isHost":false,"isSelf":false,"isSkipSelf":false,"isOptional":false,"token":{"identifier":{"reference":{"__symbol":80}}}}],"multi":false},"module":{"reference":{"__symbol":2},"diDeps":[],"lifecycleHooks":[]}},{"provider":{"token":{"identifier":{"reference":{"__symbol":88}}},"useClass":null,"useFactory":null,"useExisting":{"identifier":{"reference":{"__symbol":89}}},"multi":false},"module":{"reference":{"__symbol":2},"diDeps":[],"lifecycleHooks":[]}},{"provider":{"token":{"identifier":{"reference":{"__symbol":55}}},"useClass":null,"useFactory":{"reference":{"__symbol":96},"diDeps":[]},"useExisting":null,"deps":[],"multi":true},"module":{"reference":{"__symbol":2},"diDeps":[],"lifecycleHooks":[]}},{"provider":{"token":{"identifier":{"reference":{"__symbol":97},"diDeps":[{"isAttribute":false,"isHost":false,"isSelf":false,"isSkipSelf":false,"isOptional":false,"token":{"identifier":{"reference":{"__symbol":13}}}}],"lifecycleHooks":[]}},"useClass":{"reference":{"__symbol":97},"diDeps":[{"isAttribute":false,"isHost":false,"isSelf":false,"isSkipSelf":false,"isOptional":false,"token":{"identifier":{"reference":{"__symbol":13}}}}],"lifecycleHooks":[]},"useFactory":null,"useExisting":null,"deps":[{"isAttribute":false,"isHost":false,"isSelf":false,"isSkipSelf":false,"isOptional":false,"token":{"identifier":{"reference":{"__symbol":13}}}}],"multi":false},"module":{"reference":{"__symbol":2},"diDeps":[],"lifecycleHooks":[]}},{"provider":{"token":{"identifier":{"reference":{"__symbol":21}}},"useClass":null,"useFactory":{"reference":{"__symbol":98},"diDeps":[{"isAttribute":false,"isHost":false,"isSelf":false,"isSkipSelf":false,"isOptional":false,"token":{"identifier":{"reference":{"__symbol":97}}}}]},"useExisting":null,"deps":[{"isAttribute":false,"isHost":false,"isSelf":false,"isSkipSelf":false,"isOptional":false,"token":{"identifier":{"reference":{"__symbol":97}}}}],"multi":true},"module":{"reference":{"__symbol":2},"diDeps":[],"lifecycleHooks":[]}},{"provider":{"token":{"identifier":{"reference":{"__symbol":99}}},"useClass":null,"useFactory":{"reference":{"__symbol":100},"diDeps":[{"isAttribute":false,"isHost":false,"isSelf":false,"isSkipSelf":false,"isOptional":false,"token":{"identifier":{"reference":{"__symbol":97}}}}]},"useExisting":null,"deps":[{"isAttribute":false,"isHost":false,"isSelf":false,"isSkipSelf":false,"isOptional":false,"token":{"identifier":{"reference":{"__symbol":97}}}}],"multi":false},"module":{"reference":{"__symbol":2},"diDeps":[],"lifecycleHooks":[]}},{"provider":{"token":{"identifier":{"reference":{"__symbol":101}}},"useClass":null,"useFactory":null,"useExisting":{"identifier":{"reference":{"__symbol":99}}},"multi":true},"module":{"reference":{"__symbol":2},"diDeps":[],"lifecycleHooks":[]}},{"provider":{"token":{"identifier":{"reference":{"__symbol":102}}},"useClass":null,"useFactory":{"reference":{"__symbol":0},"diDeps":[{"isAttribute":false,"isHost":false,"isSelf":false,"isSkipSelf":false,"isOptional":false,"token":{"identifier":{"reference":{"__symbol":60}}}}]},"useExisting":null,"deps":[{"isAttribute":false,"isHost":false,"isSelf":false,"isSkipSelf":false,"isOptional":false,"token":{"identifier":{"reference":{"__symbol":60}}}}],"multi":false},"module":{"reference":{"__symbol":2},"diDeps":[],"lifecycleHooks":[]}},{"provider":{"token":{"identifier":{"reference":{"__symbol":103}}},"useClass":{"reference":{"__symbol":104},"diDeps":[],"lifecycleHooks":[]},"useFactory":null,"useExisting":null,"deps":[],"multi":false},"module":{"reference":{"__symbol":2},"diDeps":[],"lifecycleHooks":[]}},{"provider":{"token":{"identifier":{"reference":{"__symbol":105}}},"useClass":{"reference":{"__symbol":106},"diDeps":[],"lifecycleHooks":[]},"useFactory":null,"useExisting":null,"deps":[],"multi":false},"module":{"reference":{"__symbol":2},"diDeps":[],"lifecycleHooks":[]}},{"provider":{"token":{"identifier":{"reference":{"__symbol":107},"diDeps":[],"lifecycleHooks":[]}},"useClass":{"reference":{"__symbol":107},"diDeps":[],"lifecycleHooks":[]},"useFactory":null,"useExisting":null,"deps":[],"multi":false},"module":{"reference":{"__symbol":2},"diDeps":[],"lifecycleHooks":[]}},{"provider":{"token":{"identifier":{"reference":{"__symbol":108}}},"useClass":null,"useFactory":null,"useExisting":null,"multi":false},"module":{"reference":{"__symbol":2},"diDeps":[],"lifecycleHooks":[]}},{"provider":{"token":{"identifier":{"reference":{"__symbol":109},"diDeps":[{"isAttribute":false,"isHost":false,"isSelf":false,"isSkipSelf":false,"isOptional":false,"token":{"identifier":{"reference":{"__symbol":107}}}},{"isAttribute":false,"isHost":false,"isSelf":false,"isSkipSelf":false,"isOptional":false,"token":{"identifier":{"reference":{"__symbol":102}}}},{"isAttribute":false,"isHost":false,"isSelf":false,"isSkipSelf":false,"isOptional":false,"token":{"identifier":{"reference":{"__symbol":103}}}},{"isAttribute":false,"isHost":false,"isSelf":false,"isSkipSelf":false,"isOptional":false,"token":{"identifier":{"reference":{"__symbol":105}}}},{"isAttribute":false,"isHost":false,"isSelf":false,"isSkipSelf":false,"isOptional":false,"token":{"identifier":{"reference":{"__symbol":108}}}}],"lifecycleHooks":[]}},"useClass":{"reference":{"__symbol":109},"diDeps":[{"isAttribute":false,"isHost":false,"isSelf":false,"isSkipSelf":false,"isOptional":false,"token":{"identifier":{"reference":{"__symbol":107}}}},{"isAttribute":false,"isHost":false,"isSelf":false,"isSkipSelf":false,"isOptional":false,"token":{"identifier":{"reference":{"__symbol":102}}}},{"isAttribute":false,"isHost":false,"isSelf":false,"isSkipSelf":false,"isOptional":false,"token":{"identifier":{"reference":{"__symbol":103}}}},{"isAttribute":false,"isHost":false,"isSelf":false,"isSkipSelf":false,"isOptional":false,"token":{"identifier":{"reference":{"__symbol":105}}}},{"isAttribute":false,"isHost":false,"isSelf":false,"isSkipSelf":false,"isOptional":false,"token":{"identifier":{"reference":{"__symbol":108}}}}],"lifecycleHooks":[]},"useFactory":null,"useExisting":null,"deps":[{"isAttribute":false,"isHost":false,"isSelf":false,"isSkipSelf":false,"isOptional":false,"token":{"identifier":{"reference":{"__symbol":107}}}},{"isAttribute":false,"isHost":false,"isSelf":false,"isSkipSelf":false,"isOptional":false,"token":{"identifier":{"reference":{"__symbol":102}}}},{"isAttribute":false,"isHost":false,"isSelf":false,"isSkipSelf":false,"isOptional":false,"token":{"identifier":{"reference":{"__symbol":103}}}},{"isAttribute":false,"isHost":false,"isSelf":false,"isSkipSelf":false,"isOptional":false,"token":{"identifier":{"reference":{"__symbol":105}}}},{"isAttribute":false,"isHost":false,"isSelf":false,"isSkipSelf":false,"isOptional":false,"token":{"identifier":{"reference":{"__symbol":108}}}}],"multi":false},"module":{"reference":{"__symbol":2},"diDeps":[],"lifecycleHooks":[]}},{"provider":{"token":{"identifier":{"reference":{"__symbol":110},"diDeps":[{"isAttribute":false,"isHost":false,"isSelf":false,"isSkipSelf":false,"isOptional":false,"token":{"identifier":{"reference":{"__symbol":60}}}}],"lifecycleHooks":[]}},"useClass":{"reference":{"__symbol":110},"diDeps":[{"isAttribute":false,"isHost":false,"isSelf":false,"isSkipSelf":false,"isOptional":false,"token":{"identifier":{"reference":{"__symbol":60}}}}],"lifecycleHooks":[]},"useFactory":null,"useExisting":null,"deps":[{"isAttribute":false,"isHost":false,"isSelf":false,"isSkipSelf":false,"isOptional":false,"token":{"identifier":{"reference":{"__symbol":60}}}}],"multi":false},"module":{"reference":{"__symbol":2},"diDeps":[],"lifecycleHooks":[]}}],"modules":[{"reference":{"__symbol":9},"diDeps":[],"lifecycleHooks":[]},{"reference":{"__symbol":19},"diDeps":[],"lifecycleHooks":[]},{"reference":{"__symbol":35},"diDeps":[{"isAttribute":false,"isHost":false,"isSelf":false,"isSkipSelf":true,"isOptional":true,"token":{"identifier":{"reference":{"__symbol":35}}}}],"lifecycleHooks":[]},{"reference":{"__symbol":111},"diDeps":[],"lifecycleHooks":[]},{"reference":{"__symbol":58},"diDeps":[],"lifecycleHooks":[]},{"reference":{"__symbol":112},"diDeps":[{"isAttribute":false,"isHost":false,"isSelf":false,"isSkipSelf":false,"isOptional":true,"token":{"identifier":{"reference":{"__symbol":91}}}}],"lifecycleHooks":[]},{"reference":{"__symbol":64},"diDeps":[],"lifecycleHooks":[]},{"reference":{"__symbol":113},"diDeps":[],"lifecycleHooks":[]},{"reference":{"__symbol":2},"diDeps":[],"lifecycleHooks":[]}],"exportedDirectives":[],"exportedPipes":[]}}],"symbols":[{"__symbol":0,"name":"createTranslateLoader","filePath":"J:/Sources/WTW/wtw/app/app.module.d.ts"},{"__symbol":1,"name":"TranslateHttpLoader","filePath":"J:/Sources/WTW/wtw/node_modules/@ngx-translate/http-loader/index.d.ts"},{"__symbol":2,"name":"AppModule","filePath":"J:/Sources/WTW/wtw/app/app.module.d.ts"},{"__symbol":3,"name":"LoginPageComponent","filePath":"J:/Sources/WTW/wtw/app/login/login-page.component.d.ts"},{"__symbol":4,"name":"HomePageComponent","filePath":"J:/Sources/WTW/wtw/app/home/home-page.component.d.ts"},{"__symbol":5,"name":"MainAppComponent","filePath":"J:/Sources/WTW/wtw/app/main-app.component.d.ts"},{"__symbol":6,"name":"NgLocalization","filePath":"J:/Sources/WTW/wtw/node_modules/@angular/common/src/localization.d.ts"},{"__symbol":7,"name":"NgLocaleLocalization","filePath":"J:/Sources/WTW/wtw/node_modules/@angular/common/src/localization.d.ts"},{"__symbol":8,"name":"LOCALE_ID","filePath":"J:/Sources/WTW/wtw/node_modules/@angular/core/src/i18n/tokens.d.ts"},{"__symbol":9,"name":"CommonModule","filePath":"J:/Sources/WTW/wtw/node_modules/@angular/common/src/common_module.d.ts"},{"__symbol":10,"name":"ApplicationRef_","filePath":"J:/Sources/WTW/wtw/node_modules/@angular/core/src/application_ref.d.ts"},{"__symbol":11,"name":"NgZone","filePath":"J:/Sources/WTW/wtw/node_modules/@angular/core/src/zone/ng_zone.d.ts"},{"__symbol":12,"name":"Console","filePath":"J:/Sources/WTW/wtw/node_modules/@angular/core/src/console.d.ts"},{"__symbol":13,"name":"Injector","filePath":"J:/Sources/WTW/wtw/node_modules/@angular/core/src/di/injector.d.ts"},{"__symbol":14,"name":"ErrorHandler","filePath":"J:/Sources/WTW/wtw/node_modules/@angular/core/src/error_handler.d.ts"},{"__symbol":15,"name":"ComponentFactoryResolver","filePath":"J:/Sources/WTW/wtw/node_modules/@angular/core/src/linker/component_factory_resolver.d.ts"},{"__symbol":16,"name":"ApplicationInitStatus","filePath":"J:/Sources/WTW/wtw/node_modules/@angular/core/src/application_init.d.ts"},{"__symbol":17,"name":"TestabilityRegistry","filePath":"J:/Sources/WTW/wtw/node_modules/@angular/core/src/testability/testability.d.ts"},{"__symbol":18,"name":"Testability","filePath":"J:/Sources/WTW/wtw/node_modules/@angular/core/src/testability/testability.d.ts"},{"__symbol":19,"name":"ApplicationModule","filePath":"J:/Sources/WTW/wtw/node_modules/@angular/core/src/application_module.d.ts"},{"__symbol":20,"name":"ApplicationRef","filePath":"J:/Sources/WTW/wtw/node_modules/@angular/core/src/application_ref.d.ts"},{"__symbol":21,"name":"APP_INITIALIZER","filePath":"J:/Sources/WTW/wtw/node_modules/@angular/core/src/application_init.d.ts"},{"__symbol":22,"name":"Compiler","filePath":"J:/Sources/WTW/wtw/node_modules/@angular/core/src/linker/compiler.d.ts"},{"__symbol":23,"name":"APP_ID","filePath":"J:/Sources/WTW/wtw/node_modules/@angular/core/src/application_tokens.d.ts"},{"__symbol":24,"name":"_appIdRandomProviderFactory","filePath":"J:/Sources/WTW/wtw/node_modules/@angular/core/src/application_tokens.d.ts"},{"__symbol":25,"name":"ViewUtils","filePath":"J:/Sources/WTW/wtw/node_modules/@angular/core/src/linker/view_utils.d.ts"},{"__symbol":26,"name":"RootRenderer","filePath":"J:/Sources/WTW/wtw/node_modules/@angular/core/src/render/api.d.ts"},{"__symbol":27,"name":"Sanitizer","filePath":"J:/Sources/WTW/wtw/node_modules/@angular/core/src/security.d.ts"},{"__symbol":28,"name":"AnimationQueue","filePath":"J:/Sources/WTW/wtw/node_modules/@angular/core/src/animation/animation_queue.d.ts"},{"__symbol":29,"name":"IterableDiffers","filePath":"J:/Sources/WTW/wtw/node_modules/@angular/core/src/change_detection/differs/iterable_differs.d.ts"},{"__symbol":30,"name":"_iterableDiffersFactory","filePath":"J:/Sources/WTW/wtw/node_modules/@angular/core/src/application_module.d.ts"},{"__symbol":31,"name":"KeyValueDiffers","filePath":"J:/Sources/WTW/wtw/node_modules/@angular/core/src/change_detection/differs/keyvalue_differs.d.ts"},{"__symbol":32,"name":"_keyValueDiffersFactory","filePath":"J:/Sources/WTW/wtw/node_modules/@angular/core/src/application_module.d.ts"},{"__symbol":33,"name":"_localeFactory","filePath":"J:/Sources/WTW/wtw/node_modules/@angular/core/src/application_module.d.ts"},{"__symbol":34,"name":"DomSanitizer","filePath":"J:/Sources/WTW/wtw/node_modules/@angular/platform-browser/src/security/dom_sanitization_service.d.ts"},{"__symbol":35,"name":"BrowserModule","filePath":"J:/Sources/WTW/wtw/node_modules/@angular/platform-browser/src/browser.d.ts"},{"__symbol":36,"name":"DomSanitizerImpl","filePath":"J:/Sources/WTW/wtw/node_modules/@angular/platform-browser/src/security/dom_sanitization_service.d.ts"},{"__symbol":37,"name":"errorHandler","filePath":"J:/Sources/WTW/wtw/node_modules/@angular/platform-browser/src/browser.d.ts"},{"__symbol":38,"name":"DOCUMENT","filePath":"J:/Sources/WTW/wtw/node_modules/@angular/platform-browser/src/dom/dom_tokens.d.ts"},{"__symbol":39,"name":"_document","filePath":"J:/Sources/WTW/wtw/node_modules/@angular/platform-browser/src/browser.d.ts"},{"__symbol":40,"name":"EVENT_MANAGER_PLUGINS","filePath":"J:/Sources/WTW/wtw/node_modules/@angular/platform-browser/src/dom/events/event_manager.d.ts"},{"__symbol":41,"name":"DomEventsPlugin","filePath":"J:/Sources/WTW/wtw/node_modules/@angular/platform-browser/src/dom/events/dom_events.d.ts"},{"__symbol":42,"name":"KeyEventsPlugin","filePath":"J:/Sources/WTW/wtw/node_modules/@angular/platform-browser/src/dom/events/key_events.d.ts"},{"__symbol":43,"name":"HammerGesturesPlugin","filePath":"J:/Sources/WTW/wtw/node_modules/@angular/platform-browser/src/dom/events/hammer_gestures.d.ts"},{"__symbol":44,"name":"HAMMER_GESTURE_CONFIG","filePath":"J:/Sources/WTW/wtw/node_modules/@angular/platform-browser/src/dom/events/hammer_gestures.d.ts"},{"__symbol":45,"name":"HammerGestureConfig","filePath":"J:/Sources/WTW/wtw/node_modules/@angular/platform-browser/src/dom/events/hammer_gestures.d.ts"},{"__symbol":46,"name":"DomRootRenderer","filePath":"J:/Sources/WTW/wtw/node_modules/@angular/platform-browser/src/dom/dom_renderer.d.ts"},{"__symbol":47,"name":"DomRootRenderer_","filePath":"J:/Sources/WTW/wtw/node_modules/@angular/platform-browser/src/dom/dom_renderer.d.ts"},{"__symbol":48,"name":"EventManager","filePath":"J:/Sources/WTW/wtw/node_modules/@angular/platform-browser/src/dom/events/event_manager.d.ts"},{"__symbol":49,"name":"DomSharedStylesHost","filePath":"J:/Sources/WTW/wtw/node_modules/@angular/platform-browser/src/dom/shared_styles_host.d.ts"},{"__symbol":50,"name":"AnimationDriver","filePath":"J:/Sources/WTW/wtw/node_modules/@angular/platform-browser/src/dom/animation_driver.d.ts"},{"__symbol":51,"name":"SharedStylesHost","filePath":"J:/Sources/WTW/wtw/node_modules/@angular/platform-browser/src/dom/shared_styles_host.d.ts"},{"__symbol":52,"name":"_resolveDefaultAnimationDriver","filePath":"J:/Sources/WTW/wtw/node_modules/@angular/platform-browser/src/browser.d.ts"},{"__symbol":53,"name":"_createConditionalRootRenderer","filePath":"J:/Sources/WTW/wtw/node_modules/@angular/platform-browser/src/dom/debug/ng_probe.d.ts"},{"__symbol":54,"name":"NgProbeToken","filePath":"J:/Sources/WTW/wtw/node_modules/@angular/platform-browser/src/dom/debug/ng_probe.d.ts"},{"__symbol":55,"name":"NgProbeToken","filePath":"J:/Sources/WTW/wtw/node_modules/@angular/core/src/application_ref.d.ts"},{"__symbol":56,"name":"Title","filePath":"J:/Sources/WTW/wtw/node_modules/@angular/platform-browser/src/browser/title.d.ts"},{"__symbol":57,"name":"FormBuilder","filePath":"J:/Sources/WTW/wtw/node_modules/@angular/forms/src/form_builder.d.ts"},{"__symbol":58,"name":"ReactiveFormsModule","filePath":"J:/Sources/WTW/wtw/node_modules/@angular/forms/src/form_providers.d.ts"},{"__symbol":59,"name":"RadioControlRegistry","filePath":"J:/Sources/WTW/wtw/node_modules/@angular/forms/src/directives/radio_control_value_accessor.d.ts"},{"__symbol":60,"name":"Http","filePath":"J:/Sources/WTW/wtw/node_modules/@angular/http/src/http.d.ts"},{"__symbol":61,"name":"httpFactory","filePath":"J:/Sources/WTW/wtw/node_modules/@angular/http/src/http_module.d.ts"},{"__symbol":62,"name":"XHRBackend","filePath":"J:/Sources/WTW/wtw/node_modules/@angular/http/src/backends/xhr_backend.d.ts"},{"__symbol":63,"name":"RequestOptions","filePath":"J:/Sources/WTW/wtw/node_modules/@angular/http/src/base_request_options.d.ts"},{"__symbol":64,"name":"HttpModule","filePath":"J:/Sources/WTW/wtw/node_modules/@angular/http/src/http_module.d.ts"},{"__symbol":65,"name":"BrowserXhr","filePath":"J:/Sources/WTW/wtw/node_modules/@angular/http/src/backends/browser_xhr.d.ts"},{"__symbol":66,"name":"BaseRequestOptions","filePath":"J:/Sources/WTW/wtw/node_modules/@angular/http/src/base_request_options.d.ts"},{"__symbol":67,"name":"ResponseOptions","filePath":"J:/Sources/WTW/wtw/node_modules/@angular/http/src/base_response_options.d.ts"},{"__symbol":68,"name":"BaseResponseOptions","filePath":"J:/Sources/WTW/wtw/node_modules/@angular/http/src/base_response_options.d.ts"},{"__symbol":69,"name":"XSRFStrategy","filePath":"J:/Sources/WTW/wtw/node_modules/@angular/http/src/interfaces.d.ts"},{"__symbol":70,"name":"_createDefaultCookieXSRFStrategy","filePath":"J:/Sources/WTW/wtw/node_modules/@angular/http/src/http_module.d.ts"},{"__symbol":71,"name":"Location","filePath":"J:/Sources/WTW/wtw/node_modules/@angular/common/src/location/location.d.ts"},{"__symbol":72,"name":"LocationStrategy","filePath":"J:/Sources/WTW/wtw/node_modules/@angular/common/src/location/location_strategy.d.ts"},{"__symbol":73,"name":"UrlSerializer","filePath":"J:/Sources/WTW/wtw/node_modules/@angular/router/src/url_tree.d.ts"},{"__symbol":74,"name":"DefaultUrlSerializer","filePath":"J:/Sources/WTW/wtw/node_modules/@angular/router/src/url_tree.d.ts"},{"__symbol":75,"name":"Router","filePath":"J:/Sources/WTW/wtw/node_modules/@angular/router/src/router.d.ts"},{"__symbol":76,"name":"setupRouter","filePath":"J:/Sources/WTW/wtw/node_modules/@angular/router/src/router_module.d.ts"},{"__symbol":77,"name":"RouterOutletMap","filePath":"J:/Sources/WTW/wtw/node_modules/@angular/router/src/router_outlet_map.d.ts"},{"__symbol":78,"name":"NgModuleFactoryLoader","filePath":"J:/Sources/WTW/wtw/node_modules/@angular/core/src/linker/ng_module_factory_loader.d.ts"},{"__symbol":79,"name":"ROUTES","filePath":"J:/Sources/WTW/wtw/node_modules/@angular/router/src/router_config_loader.d.ts"},{"__symbol":80,"name":"ROUTER_CONFIGURATION","filePath":"J:/Sources/WTW/wtw/node_modules/@angular/router/src/router_module.d.ts"},{"__symbol":81,"name":"UrlHandlingStrategy","filePath":"J:/Sources/WTW/wtw/node_modules/@angular/router/src/url_handling_strategy.d.ts"},{"__symbol":82,"name":"RouteReuseStrategy","filePath":"J:/Sources/WTW/wtw/node_modules/@angular/router/src/route_reuse_strategy.d.ts"},{"__symbol":83,"name":"ActivatedRoute","filePath":"J:/Sources/WTW/wtw/node_modules/@angular/router/src/router_state.d.ts"},{"__symbol":84,"name":"rootRoute","filePath":"J:/Sources/WTW/wtw/node_modules/@angular/router/src/router_module.d.ts"},{"__symbol":85,"name":"SystemJsNgModuleLoader","filePath":"J:/Sources/WTW/wtw/node_modules/@angular/core/src/linker/system_js_ng_module_factory_loader.d.ts"},{"__symbol":86,"name":"SystemJsNgModuleLoaderConfig","filePath":"J:/Sources/WTW/wtw/node_modules/@angular/core/src/linker/system_js_ng_module_factory_loader.d.ts"},{"__symbol":87,"name":"RouterPreloader","filePath":"J:/Sources/WTW/wtw/node_modules/@angular/router/src/router_preloader.d.ts"},{"__symbol":88,"name":"PreloadingStrategy","filePath":"J:/Sources/WTW/wtw/node_modules/@angular/router/src/router_preloader.d.ts"},{"__symbol":89,"name":"NoPreloading","filePath":"J:/Sources/WTW/wtw/node_modules/@angular/router/src/router_preloader.d.ts"},{"__symbol":90,"name":"PreloadAllModules","filePath":"J:/Sources/WTW/wtw/node_modules/@angular/router/src/router_preloader.d.ts"},{"__symbol":91,"name":"ROUTER_FORROOT_GUARD","filePath":"J:/Sources/WTW/wtw/node_modules/@angular/router/src/router_module.d.ts"},{"__symbol":92,"name":"provideForRootGuard","filePath":"J:/Sources/WTW/wtw/node_modules/@angular/router/src/router_module.d.ts"},{"__symbol":93,"name":"provideLocationStrategy","filePath":"J:/Sources/WTW/wtw/node_modules/@angular/router/src/router_module.d.ts"},{"__symbol":94,"name":"PlatformLocation","filePath":"J:/Sources/WTW/wtw/node_modules/@angular/common/src/location/platform_location.d.ts"},{"__symbol":95,"name":"APP_BASE_HREF","filePath":"J:/Sources/WTW/wtw/node_modules/@angular/common/src/location/location_strategy.d.ts"},{"__symbol":96,"name":"routerNgProbeToken","filePath":"J:/Sources/WTW/wtw/node_modules/@angular/router/src/router_module.d.ts"},{"__symbol":97,"name":"RouterInitializer","filePath":"J:/Sources/WTW/wtw/node_modules/@angular/router/src/router_module.d.ts"},{"__symbol":98,"name":"getAppInitializer","filePath":"J:/Sources/WTW/wtw/node_modules/@angular/router/src/router_module.d.ts"},{"__symbol":99,"name":"ROUTER_INITIALIZER","filePath":"J:/Sources/WTW/wtw/node_modules/@angular/router/src/router_module.d.ts"},{"__symbol":100,"name":"getBootstrapListener","filePath":"J:/Sources/WTW/wtw/node_modules/@angular/router/src/router_module.d.ts"},{"__symbol":101,"name":"APP_BOOTSTRAP_LISTENER","filePath":"J:/Sources/WTW/wtw/node_modules/@angular/core/src/application_tokens.d.ts"},{"__symbol":102,"name":"TranslateLoader","filePath":"J:/Sources/WTW/wtw/node_modules/@ngx-translate/core/src/translate.loader.d.ts"},{"__symbol":103,"name":"TranslateParser","filePath":"J:/Sources/WTW/wtw/node_modules/@ngx-translate/core/src/translate.parser.d.ts"},{"__symbol":104,"name":"TranslateDefaultParser","filePath":"J:/Sources/WTW/wtw/node_modules/@ngx-translate/core/src/translate.parser.d.ts"},{"__symbol":105,"name":"MissingTranslationHandler","filePath":"J:/Sources/WTW/wtw/node_modules/@ngx-translate/core/src/missing-translation-handler.d.ts"},{"__symbol":106,"name":"FakeMissingTranslationHandler","filePath":"J:/Sources/WTW/wtw/node_modules/@ngx-translate/core/src/missing-translation-handler.d.ts"},{"__symbol":107,"name":"TranslateStore","filePath":"J:/Sources/WTW/wtw/node_modules/@ngx-translate/core/src/translate.store.d.ts"},{"__symbol":108,"name":"USE_STORE","filePath":"J:/Sources/WTW/wtw/node_modules/@ngx-translate/core/src/translate.service.d.ts"},{"__symbol":109,"name":"TranslateService","filePath":"J:/Sources/WTW/wtw/node_modules/@ngx-translate/core/src/translate.service.d.ts"},{"__symbol":110,"name":"AuthService","filePath":"J:/Sources/WTW/wtw/app/auth/auth.service.d.ts"},{"__symbol":111,"name":"InternalFormsSharedModule","filePath":"J:/Sources/WTW/wtw/node_modules/@angular/forms/src/directives.d.ts"},{"__symbol":112,"name":"RouterModule","filePath":"J:/Sources/WTW/wtw/node_modules/@angular/router/src/router_module.d.ts"},{"__symbol":113,"name":"TranslateModule","filePath":"J:/Sources/WTW/wtw/node_modules/@ngx-translate/core/index.d.ts"}]}